bindiffscript/__init__.py
bindiffscript/cli.py
bindiffscript-0.3.0.dist-info/METADATA
bindiffscript-0.3.0.dist-info/WHEEL
bindiffscript-0.3.0.dist-info/entry_points.txt
bindiffscript-0.3.0.dist-info/RECORD
