Metadata-Version: 2.4
Name: bindiffscript
Version: 0.3.0
Summary: bindiffscript
Project-URL: Repository, https://github.com/frans-fuerst/bindiffscript.git
Author-email: Frans Fürst <frans.fuerst+gitlab@protonmail.com>
Requires-Python: <3.14,>=3.12
Requires-Dist: pyyaml>=6.0.2
Requires-Dist: rich>=14.1.0
